[
   {
      "gtin" : "",
      "uom" : "EACH",
      "itemID" : "15345672179",
      "bopus" : "true",
      "lotNumber" : "1534567",
      "shippable" : "true",
      "productLine" : "153",
      "purchaseType" : "Fashion",
      "isSubstitutionAllowed" : "N",
      "itemProcessingTime" : "10"
   },
   {
      "gtin" : "",
      "uom" : "EACH",
      "itemID" : "15345672180",
      "bopus" : "true",
      "lotNumber" : "1534567",
      "shippable" : "true",
      "productLine" : "153",
      "purchaseType" : "Fashion",
      "isSubstitutionAllowed" : "N",
      "itemProcessingTime" : "10"
   }
]