[
   {
      "gtin" : "",
      "uom" : "EACH",
      "itemID" : "15345672225",
      "bopus" : "true",
      "lotNumber" : "1534567",
      "shippable" : "true",
      "productLine" : "153",
      "purchaseType" : "Fashion",
      "isSubstitutionAllowed" : "N",
      "itemProcessingTime" : "10"
   },
   
   {
      "gtin" : "",
      "uom" : "EACH",
      "itemID" : "15345672226",
      "bopus" : "true",
      "lotNumber" : "1534567",
      "shippable" : "true",
      "productLine" : "153",
      "purchaseType" : "Fashion193",
      "isSubstitutionAllowed" : "N",
      "itemProcessingTime" : "10"
   },
   {
      "gtin" : "",
      "uom" : "EACH",
      "itemID" : "15345672227",
      "bopus" : "true",
      "lotNumber" : "1534567",
      "shippable" : "true",
      "productLine" : "153",
      "purchaseType" : "Fashion",
      "isSubstitutionAllowed" : "N",
      "itemProcessingTime" : "10"
   },
   
   {
      "gtin" : "",
      "uom" : "EACH",
      "itemID" : "17145672228",
      "bopus" : "true",
      "lotNumber" : "1714567",
      "shippable" : "true",
      "productLine" : "171",
      "purchaseType" : "Fashion",
      "isSubstitutionAllowed" : "N",
      "itemProcessingTime" : "10"
   }
]