{
    "message": "Success",
    "body": [
        {
            "partiallyReservedQty": 0,
            "shortageQty": 0,
            "orgCode": "JCP",
            "reservedQty": 3,
            "requestLine": {
                "deliveryMethod": null,
                "channel": null,
                "lineID": "2",
                "storeID": "2953",
                "itemID": "7063000-3053",
                "schedule": false,
                "uom": "EACH",
                "shippable": true,
                "reservationID": "c9dde97c-ec73-482c-a871-c7f89291c5e3",
                "procurementAllowed": false,
                "qty": 3,
                "bopus": false,
                "increaseCapacity": null,
                "shutdown": false
            },
            "problemType": "SUCCESS"
        },
        {
            "partiallyReservedQty": 0,
            "shortageQty": 0,
            "orgCode": "JCP",
            "reservedQty": 3,
            "requestLine": {
                "deliveryMethod": null,
                "channel": null,
                "lineID": "1",
                "storeID": "2952",
                "itemID": "7063000-3053",
                "schedule": false,
                "uom": "EACH",
                "shippable": true,
                "reservationID": "530cadcd-2ad9-4f60-b500-56af21f78c6c",
                "procurementAllowed": false,
                "qty": 3,
                "bopus": false,
                "increaseCapacity": null,
                "shutdown": false
            },
            "problemType": "SUCCESS"
        }
    ],
    "status": 200
}