{"body":[{"status":200,"message":"Success","key":"JCP|2204|17112343028|EACH","body":{"invall":{"shipATP":40,"unconfirmeddemand":0,"ship_active":1,"Available_capacity":8,"bopusSafetyFactor":0,"bopusATP":40,"shipSafetyFactor":0,"reserveddemand":0,"bopus_active":1,"onhandsupply":40}},"warnings":null},{"status":200,"message":"Success","key":"JCP|2203|17112343028|EACH","body":{"invall":{"shipATP":38,"unconfirmeddemand":0,"ship_active":1,"Available_capacity":7,"bopusSafetyFactor":0,"bopusATP":38,"shipSafetyFactor":0,"reserveddemand":2,"bopus_active":1,"onhandsupply":40}},"warnings":null}],"status":221,"message":"Successful"}