{"body":[{"status":200,"message":"Success","key":"JCP|2342|17112343073|EACH","body":{"invall":{"shipATP":0,"unconfirmeddemand":0,"ship_active":1,"Available_capacity":7,"bopusSafetyFactor":0,"bopusATP":0,"shipSafetyFactor":0,"reserveddemand":1,"bopus_active":1,"onhandsupply":1}},"warnings":null},{"status":200,"message":"Success","key":"JCP|2341|17112343072|EACH","body":{"invall":{"shipATP":0,"unconfirmeddemand":0,"ship_active":1,"Available_capacity":8,"bopusSafetyFactor":0,"bopusATP":0,"shipSafetyFactor":0,"reserveddemand":1,"bopus_active":1,"onhandsupply":1}},"warnings":null}],"status":221,"message":"Successful"}