{
    "body": [
        {
            "warnings": null,
            "message": "Success",
            "nodeType": "Store",
            "body": {
                "invall": {
                    "isSubLotSFSExclusion": 0,
                    "isPerformanceSFSExclusion": 0,
                    "isSublotBOPUSExclusion": 0,
                    "isBelowAur": 0,
                    "unconfirmeddemand": 0,
                    "standard_capacity": 100,
                    "inventory_timestamp_low": 1398674381,
                    "isDirty": 0,
                    "bopusSafetyFactor": 0,
                    "shipSafetyFactor": 0,
                    "isOnClearance": 0,
                    "clearance_capacity_percentage": 0,
                    "reserveddemand": 0,
                    "isBopisMarkdownEligible": 1,
                    "onhandsupply": 50,
                    "inventory_timestamp_high": 360,
                    "isSFSMarkdownEligible": 1,
                    "shipATP": 50,
                    "isPerformanceBopusExclusion": 0,
                    "pickSafetyFactorSource": 0,
                    "ship_active": 1,
                    "Available_capacity": 100,
                    "shipSafetyFactorSource": 0,
                    "isActiveMarkDown": 0,
                    "bopusATP": 50,
                    "grossShipAtp": 50,
                    "bopus_active": 1,
                    "grossBopusAtp": 50
                }
            },
            "key": "JCP|1052|35145678010|EACH",
            "status": 200
        },
        {
            "warnings": null,
            "message": "Success",
            "nodeType": "Store",
            "body": {
                "invall": {
                    "isSubLotSFSExclusion": 0,
                    "isPerformanceSFSExclusion": 0,
                    "isSublotBOPUSExclusion": 0,
                    "isBelowAur": 0,
                    "unconfirmeddemand": 0,
                    "standard_capacity": 100,
                    "inventory_timestamp_low": -1284945619,
                    "isDirty": 0,
                    "bopusSafetyFactor": 0,
                    "shipSafetyFactor": 0,
                    "isOnClearance": 0,
                    "clearance_capacity_percentage": 0,
                    "reserveddemand": 0,
                    "isBopisMarkdownEligible": 1,
                    "onhandsupply": 10,
                    "inventory_timestamp_high": 359,
                    "isSFSMarkdownEligible": 1,
                    "shipATP": 10,
                    "isPerformanceBopusExclusion": 0,
                    "pickSafetyFactorSource": 0,
                    "ship_active": 1,
                    "Available_capacity": 100,
                    "shipSafetyFactorSource": 0,
                    "isActiveMarkDown": 0,
                    "bopusATP": 10,
                    "grossShipAtp": 10,
                    "bopus_active": 1,
                    "grossBopusAtp": 10
                }
            },
            "key": "JCP|1052|35145678009|EACH",
            "status": 200
        },
        {
            "warnings": null,
            "message": "Success",
            "nodeType": "Store",
            "body": {
                "invall": {
                    "isSubLotSFSExclusion": 0,
                    "isPerformanceSFSExclusion": 0,
                    "isSublotBOPUSExclusion": 0,
                    "isBelowAur": 0,
                    "unconfirmeddemand": 0,
                    "standard_capacity": 100,
                    "inventory_timestamp_low": -1284945619,
                    "isDirty": 0,
                    "bopusSafetyFactor": 0,
                    "shipSafetyFactor": 0,
                    "isOnClearance": 0,
                    "clearance_capacity_percentage": 0,
                    "reserveddemand": 0,
                    "isBopisMarkdownEligible": 1,
                    "onhandsupply": 10,
                    "inventory_timestamp_high": 359,
                    "isSFSMarkdownEligible": 1,
                    "shipATP": 10,
                    "isPerformanceBopusExclusion": 0,
                    "pickSafetyFactorSource": 0,
                    "ship_active": 1,
                    "Available_capacity": 100,
                    "shipSafetyFactorSource": 0,
                    "isActiveMarkDown": 0,
                    "bopusATP": 10,
                    "grossShipAtp": 10,
                    "bopus_active": 1,
                    "grossBopusAtp": 10
                }
            },
            "key": "JCP|1052|35145678008|EACH",
            "status": 200
        }
    ],
    "message": "Successful",
    "status": 221
}